starwhale/__init__.py
starwhale/__main__.py
starwhale/version.py
starwhale/api/__init__.py
starwhale/api/argument.py
starwhale/api/dataset.py
starwhale/api/evaluation.py
starwhale/api/experiment.py
starwhale/api/instance.py
starwhale/api/job.py
starwhale/api/metric.py
starwhale/api/model.py
starwhale/api/service.py
starwhale/api/track.py
starwhale/api/_impl/__init__.py
starwhale/api/_impl/argument.py
starwhale/api/_impl/data_store.py
starwhale/api/_impl/experiment.py
starwhale/api/_impl/instance.py
starwhale/api/_impl/metric.py
starwhale/api/_impl/model.py
starwhale/api/_impl/wrapper.py
starwhale/api/_impl/dataset/__init__.py
starwhale/api/_impl/dataset/loader.py
starwhale/api/_impl/dataset/model.py
starwhale/api/_impl/dataset/builder/__init__.py
starwhale/api/_impl/dataset/builder/mapping_builder.py
starwhale/api/_impl/evaluation/__init__.py
starwhale/api/_impl/evaluation/log.py
starwhale/api/_impl/evaluation/pipeline.py
starwhale/api/_impl/job/__init__.py
starwhale/api/_impl/job/handler.py
starwhale/api/_impl/job/model.py
starwhale/api/_impl/service/__init__.py
starwhale/api/_impl/service/service.py
starwhale/api/_impl/service/types/__init__.py
starwhale/api/_impl/service/types/llm.py
starwhale/api/_impl/service/types/text_to_img.py
starwhale/api/_impl/service/types/types.py
starwhale/api/_impl/track/__init__.py
starwhale/api/_impl/track/base.py
starwhale/api/_impl/track/collector.py
starwhale/api/_impl/track/handler.py
starwhale/api/_impl/track/hooker.py
starwhale/api/_impl/track/syncer.py
starwhale/api/_impl/track/tracker.py
starwhale/base/__init__.py
starwhale/base/bundle.py
starwhale/base/bundle_copy.py
starwhale/base/cloud.py
starwhale/base/cloud_blob_cache.py
starwhale/base/context.py
starwhale/base/data_type.py
starwhale/base/mixin.py
starwhale/base/package.py
starwhale/base/store.py
starwhale/base/tag.py
starwhale/base/type.py
starwhale/base/view.py
starwhale/base/artifact/__init__.py
starwhale/base/artifact/base.py
starwhale/base/artifact/rotated_bin.py
starwhale-0.6.15.dist-info/METADATA
starwhale-0.6.15.dist-info/WHEEL
starwhale-0.6.15.dist-info/entry_points.txt
starwhale-0.6.15.dist-info/top_level.txt
starwhale-0.6.15.dist-info/RECORD
