Metadata-Version: 2.1
Name: starwhale
Version: 0.6.15
Summary: An MLOps Platform for Model Evaluation
Home-page: https://github.com/star-whale/starwhale
Author: Starwhale Team
Author-email: developer@starwhale.ai
License: Apache License 2.0
Keywords: MLOps,AI,Starwhale,Model Evaluation
Classifier: Development Status :: 2 - Pre-Alpha
Classifier: Intended Audience :: Developers
Classifier: Intended Audience :: Science/Research
Classifier: Operating System :: OS Independent
Classifier: License :: OSI Approved :: Apache Software License
Classifier: Programming Language :: Python :: 3 :: Only
Classifier: Programming Language :: Python :: 3.7
Classifier: Programming Language :: Python :: 3.8
Classifier: Programming Language :: Python :: 3.9
Classifier: Programming Language :: Python :: 3.10
Classifier: Programming Language :: Python :: 3.11
Classifier: Programming Language :: Python :: Implementation :: CPython
Classifier: Topic :: Software Development :: Libraries
Classifier: Topic :: Software Development :: Libraries :: Python Modules
Classifier: Topic :: Scientific/Engineering :: Artificial Intelligence
Classifier: Topic :: System :: Logging
Classifier: Topic :: System :: Monitoring
Requires-Python: >=3.7, <3.12
Requires-Dist: click-option-group ==0.5.5
Requires-Dist: click >=8.0.4
Requires-Dist: shellingham >=1.4.0
Requires-Dist: attrs >=21.4.0
Requires-Dist: pyyaml >=6.0
Requires-Dist: cattrs >=1.7.1
Requires-Dist: requests >=2.1.0
Requires-Dist: requests-toolbelt >=0.9.0
Requires-Dist: loguru ==0.6.0
Requires-Dist: conda-pack ==0.6.0
Requires-Dist: virtualenv >=13.0.0
Requires-Dist: fs >=2.4.0
Requires-Dist: typing-extensions >=4.0.0
Requires-Dist: commonmark >=0.9.1
Requires-Dist: textual ==0.1.18
Requires-Dist: jsonlines ==3.0.0
Requires-Dist: boto3 >=1.26.14
Requires-Dist: scikit-learn >=0.20.0
Requires-Dist: dill >=0.3.6
Requires-Dist: packaging >=21.3
Requires-Dist: pyarrow >=8.0.0
Requires-Dist: Jinja2 >=3.1.2
Requires-Dist: tenacity <=8.3.0,>=8.0.1
Requires-Dist: psutil >=5.5.0
Requires-Dist: GitPython >=3.1.24
Requires-Dist: filelock
Requires-Dist: fastapi
Requires-Dist: orjson
Requires-Dist: starlette
Requires-Dist: protobuf >=3.19.0
Requires-Dist: types-protobuf >=3.19.0
Requires-Dist: lz4 >=3.1.10
Requires-Dist: trio >=0.22.0
Requires-Dist: httpx >=0.22.0
Requires-Dist: urllib3 <1.27
Requires-Dist: pydantic
Requires-Dist: sortedcontainers
Requires-Dist: importlib-resources
Requires-Dist: importlib-metadata <=4.2.0,>=4.0.0 ; python_version < "3.8"
Requires-Dist: email-validator <=2.0.0 ; python_version < "3.8"
Provides-Extra: all
Requires-Dist: trio >=0.22.0 ; extra == 'all'
Requires-Dist: fastapi ; extra == 'all'
Requires-Dist: click-option-group ==0.5.5 ; extra == 'all'
Requires-Dist: conda-pack ==0.6.0 ; extra == 'all'
Requires-Dist: click >=8.0.4 ; extra == 'all'
Requires-Dist: lz4 >=3.1.10 ; extra == 'all'
Requires-Dist: importlib-resources ; extra == 'all'
Requires-Dist: uvicorn ; extra == 'all'
Requires-Dist: loguru ==0.6.0 ; extra == 'all'
Requires-Dist: virtualenv >=13.0.0 ; extra == 'all'
Requires-Dist: cattrs >=1.7.1 ; extra == 'all'
Requires-Dist: GitPython >=3.1.24 ; extra == 'all'
Requires-Dist: packaging >=21.3 ; extra == 'all'
Requires-Dist: soundfile ; extra == 'all'
Requires-Dist: httpx >=0.22.0 ; extra == 'all'
Requires-Dist: attrs >=21.4.0 ; extra == 'all'
Requires-Dist: fs >=2.4.0 ; extra == 'all'
Requires-Dist: shellingham >=1.4.0 ; extra == 'all'
Requires-Dist: requests >=2.1.0 ; extra == 'all'
Requires-Dist: typing-extensions >=4.0.0 ; extra == 'all'
Requires-Dist: urllib3 <1.27 ; extra == 'all'
Requires-Dist: jsonlines ==3.0.0 ; extra == 'all'
Requires-Dist: pillow ; extra == 'all'
Requires-Dist: dill >=0.3.6 ; extra == 'all'
Requires-Dist: pyarrow >=8.0.0 ; extra == 'all'
Requires-Dist: sortedcontainers ; extra == 'all'
Requires-Dist: commonmark >=0.9.1 ; extra == 'all'
Requires-Dist: Jinja2 >=3.1.2 ; extra == 'all'
Requires-Dist: protobuf >=3.19.0 ; extra == 'all'
Requires-Dist: tenacity <=8.3.0,>=8.0.1 ; extra == 'all'
Requires-Dist: types-protobuf >=3.19.0 ; extra == 'all'
Requires-Dist: orjson ; extra == 'all'
Requires-Dist: requests-toolbelt >=0.9.0 ; extra == 'all'
Requires-Dist: boto3 >=1.26.14 ; extra == 'all'
Requires-Dist: starlette ; extra == 'all'
Requires-Dist: pydantic ; extra == 'all'
Requires-Dist: filelock ; extra == 'all'
Requires-Dist: pyyaml >=6.0 ; extra == 'all'
Requires-Dist: scikit-learn >=0.20.0 ; extra == 'all'
Requires-Dist: psutil >=5.5.0 ; extra == 'all'
Requires-Dist: textual ==0.1.18 ; extra == 'all'
Requires-Dist: email-validator <=2.0.0 ; (python_version < "3.8") and extra == 'all'
Requires-Dist: importlib-metadata <=4.2.0,>=4.0.0 ; (python_version < "3.8") and extra == 'all'
Provides-Extra: audio
Requires-Dist: soundfile ; extra == 'audio'
Provides-Extra: image
Requires-Dist: pillow ; extra == 'image'
Provides-Extra: serve
Requires-Dist: uvicorn ; extra == 'serve'
